{
  "runId": "a6fcdad5-8445-4c4f-81a0-6e99444c2768",
  "customerId": "pfds-vertex",
  "createdAt": "2025-11-24T22:21:49.649Z",
  "documents": [],
  "profile": {
    "customerId": "pfds-vertex",
    "addressEvidence": [],
    "bankAccounts": [],
    "historical_addresses": [],
    "lastUpdatedAt": "2025-11-24T22:21:49.647Z"
  },
  "validation": {
    "customerId": "pfds-vertex",
    "score": 0,
    "flags": [
      {
        "code": "OTHER",
        "level": "warning",
        "message": "No UBOs (>25%) detected from shareholder structure."
      },
      {
        "code": "OTHER",
        "level": "warning",
        "message": "No Full Power signatories detected."
      },
      {
        "code": "LOW_DOC_COVERAGE",
        "level": "critical",
        "message": "Missing Company Identity (Acta Constitutiva)."
      },
      {
        "code": "LOW_DOC_COVERAGE",
        "level": "critical",
        "message": "Missing Tax Profile (SAT Constancia)."
      },
      {
        "code": "LOW_DOC_COVERAGE",
        "level": "critical",
        "message": "No Proof of Address or Bank Statements provided."
      }
    ],
    "generatedAt": "2025-11-24T22:21:49.649Z"
  }
}